qwed_finance/__init__.py
qwed_finance/calendar_guard.py
qwed_finance/compliance_guard.py
qwed_finance/cross_guard.py
qwed_finance/derivatives_guard.py
qwed_finance/finance_verifier.py
qwed_finance/message_guard.py
qwed_finance/query_guard.py
qwed_finance/schemas.py
qwed_finance/integrations/__init__.py
qwed_finance/integrations/open_responses.py
qwed_finance/integrations/ucp.py
qwed_finance/models/__init__.py
qwed_finance/models/receipt.py
qwed_finance-1.2.0.dist-info/licenses/LICENSE
qwed_finance-1.2.0.dist-info/METADATA
qwed_finance-1.2.0.dist-info/WHEEL
qwed_finance-1.2.0.dist-info/top_level.txt
qwed_finance-1.2.0.dist-info/RECORD
