Metadata-Version: 2.4
Name: qwed-finance
Version: 1.2.0
Summary: Deterministic verification middleware for banking and financial AI
Author-email: Rahul Dass <rahul@qwedai.com>
License: Apache-2.0
Project-URL: Homepage, https://github.com/QWED-AI/qwed-finance
Project-URL: Documentation, https://docs.qwedai.com
Project-URL: Repository, https://github.com/QWED-AI/qwed-finance
Project-URL: Issues, https://github.com/QWED-AI/qwed-finance/issues
Keywords: ai,verification,finance,banking,llm,deterministic,npv,irr,loan,amortization
Classifier: Development Status :: 3 - Alpha
Classifier: Intended Audience :: Developers
Classifier: Intended Audience :: Financial and Insurance Industry
Classifier: License :: OSI Approved :: Apache Software License
Classifier: Programming Language :: Python :: 3
Classifier: Programming Language :: Python :: 3.10
Classifier: Programming Language :: Python :: 3.11
Classifier: Programming Language :: Python :: 3.12
Classifier: Topic :: Office/Business :: Financial
Classifier: Topic :: Scientific/Engineering :: Artificial Intelligence
Requires-Python: >=3.10
License-File: LICENSE
Requires-Dist: sympy>=1.12
Provides-Extra: dev
Requires-Dist: pytest>=7.0; extra == "dev"
Requires-Dist: pytest-cov>=4.0; extra == "dev"
Requires-Dist: black>=23.0; extra == "dev"
Requires-Dist: ruff>=0.1.0; extra == "dev"
Dynamic: license-file
